mcp_server_biliscribe/__init__.py
mcp_server_biliscribe/__main__.py
mcp_server_biliscribe/process.py
mcp_server_biliscribe/server.py
mcp_server_biliscribe/utils.py
mcp_server_biliscribe-0.9.0.dist-info/METADATA
mcp_server_biliscribe-0.9.0.dist-info/WHEEL
mcp_server_biliscribe-0.9.0.dist-info/entry_points.txt
mcp_server_biliscribe-0.9.0.dist-info/RECORD
